{
  "heartbeatInterval": "60",
  "checkInterval": "30",
  "checkMasterSlaveDelayInterval": "120",
  "masterSlaveDelayTimeout": "600000",
  "checkFullPullInterval": "60",
  "deleteFullPullOldVersionInterval": "3",
  "maxAlarmCnt": "1",
  "heartBeatTimeout": "600000",
  "heartBeatTimeoutAdditional": {},
  "fullPullTimeout": "600000",
  "alarmTtl": "21600000",
  "lifeInterval": "60",
  "correcteValue": "0",
  "fullPullCorrecteValue": "0",
  "fullPullSliceMaxPending": "10000",
  "leaderPath": "/DBus/HeartBeat/Leader",
  "controlPath": "/DBus/HeartBeat/Control",
  "monitorPath": "/DBus/HeartBeat/Monitor",
  "monitorFullPullPath": "/DBus/FullPuller",
  "projectMonitorPath": "/DBus/HeartBeat/ProjectMonitor",
  "excludeSchema": "'monitor'",
  "checkPointPerHeartBeatCnt": "1",
  "fullPullOldVersionCnt": "3",
  "adminSMSNo": "13800138000",
  "adminUseSMS": "N",
  "adminEmail": "",
  "alarmSendEmail": "",
  "alarmMailSMTPAddress": "",
  "alarmMailSMTPPort": "",
  "alarmMailUser": "",
  "alarmMailPass": "",
  "adminUseEmail": "N",
  "additionalNotify": {},
  "checkMysqlBinlogInterval": "600"
}